fbdl_core/__init__.py
fbdl_core/fbdl.py
fbdl_core-0.0.4.dist-info/LICENSE
fbdl_core-0.0.4.dist-info/METADATA
fbdl_core-0.0.4.dist-info/WHEEL
fbdl_core-0.0.4.dist-info/entry_points.txt
fbdl_core-0.0.4.dist-info/top_level.txt
fbdl_core-0.0.4.dist-info/RECORD
