Metadata-Version: 2.1
Name: fbdl-core
Version: 0.0.4
Summary: Modul untuk mengunduh video dari Facebook melalui terminal.
Home-page: https://github.com/AntonThomz/fbdl-core
Author: AntonThomzz
Author-email: antonthomzz@gmail.com
Classifier: Programming Language :: Python :: 3
Classifier: License :: OSI Approved :: MIT License
Classifier: Operating System :: OS Independent
Requires-Python: >=3.6
License-File: LICENSE
